wolfhece/Coordinates_operations.py
wolfhece/CpGrid.py
wolfhece/GraphNotebook.py
wolfhece/GraphProfile.py
wolfhece/Lidar2002.py
wolfhece/ManageParams.py
wolfhece/Model1D.py
wolfhece/MulticriteriAnalysis.py
wolfhece/PandasGrid.py
wolfhece/PyConfig.py
wolfhece/PyCrosssections.py
wolfhece/PyDraw.py
wolfhece/PyGui.py
wolfhece/PyGuiHydrology.py
wolfhece/PyHydrographs.py
wolfhece/PyPalette.py
wolfhece/PyParams.py
wolfhece/PyPictures.py
wolfhece/PyTranslate.py
wolfhece/PyVertex.py
wolfhece/PyVertexvectors.py
wolfhece/PyWMS.py
wolfhece/RatingCurve.py
wolfhece/RatingCurveData.py
wolfhece/RatingCurve_xml.py
wolfhece/ReadDataDCENN.py
wolfhece/Results2DGPU.py
wolfhece/__init__.py
wolfhece/_add_path.py
wolfhece/analyze_poly.py
wolfhece/analyze_vect.py
wolfhece/channel_rough_ramp.py
wolfhece/cli.py
wolfhece/color_constants.py
wolfhece/compare_series.py
wolfhece/dike.py
wolfhece/drawing_obj.py
wolfhece/eikonal.py
wolfhece/flow_SPWMI.py
wolfhece/friction_law.py
wolfhece/gpuview.py
wolfhece/images_tiles.py
wolfhece/import_ascfiles.py
wolfhece/ins.py
wolfhece/interpolating_raster.py
wolfhece/irm_alaro.py
wolfhece/irm_qdf.py
wolfhece/ismember.py
wolfhece/lagrange_multiplier.py
wolfhece/lifewatch.py
wolfhece/matplotlib_fig.py
wolfhece/multiprojects.py
wolfhece/os_check.py
wolfhece/picc.py
wolfhece/pidcontroller.py
wolfhece/pyGui1D.py
wolfhece/pyLandUseFlanders.py
wolfhece/pybridges.py
wolfhece/pydike.py
wolfhece/pydownloader.py
wolfhece/pylogging.py
wolfhece/pypolygons_scen.py
wolfhece/pyshields.py
wolfhece/pyviews.py
wolfhece/pywalous.py
wolfhece/rain_SPWMI.py
wolfhece/synthetic_dike.py
wolfhece/textpillow.py
wolfhece/tools2d_dll.py
wolfhece/tools_mpl.py
wolfhece/toolshydrology_dll.py
wolfhece/wolf_array.py
wolfhece/wolf_hist.py
wolfhece/wolf_texture.py
wolfhece/wolf_tiles.py
wolfhece/wolf_vrt.py
wolfhece/wolf_zi_db.py
wolfhece/wolfresults_2D.py
wolfhece/xyz_file.py
wolfhece/acceptability/Parallels.py
wolfhece/acceptability/__init__.py
wolfhece/acceptability/_add_path.py
wolfhece-2.2.56.dist-info/METADATA
wolfhece-2.2.56.dist-info/WHEEL
wolfhece-2.2.56.dist-info/entry_points.txt
wolfhece-2.2.56.dist-info/top_level.txt
wolfhece-2.2.56.dist-info/RECORD
