Metadata-Version: 2.4
Name: wolfhece
Version: 2.2.56
Author-email: Pierre Archambeau <pierre.archambeau@uliege.be>
Project-URL: Homepage, https://uee.uliege.be/hece
Project-URL: Issues, https://uee.uliege.be/hece
Classifier: Programming Language :: Python :: 3.10
Classifier: Programming Language :: Python :: 3.11
Classifier: Programming Language :: Python :: 3.12
Classifier: Operating System :: Microsoft :: Windows :: Windows 10
Classifier: Operating System :: Microsoft :: Windows :: Windows 11
Classifier: Operating System :: POSIX :: Linux
Classifier: Topic :: Scientific/Engineering :: Physics
Requires-Python: <3.13,>=3.10
Requires-Dist: wolf-libs
Requires-Dist: wxpython==4.2.*
Requires-Dist: pyogrio
Requires-Dist: fiona
Requires-Dist: msvc-runtime
Requires-Dist: colorlog==6.7.*
Requires-Dist: intel-fortran-rt
Requires-Dist: scikit-learn
Requires-Dist: cryptography
Requires-Dist: jax==0.5.3
Requires-Dist: triangle
Requires-Dist: numpy==2.1.*
Requires-Dist: pyopengl==3.1.*
Requires-Dist: pandas
Requires-Dist: geopandas
Requires-Dist: scipy
Requires-Dist: pillow
Requires-Dist: cython
Requires-Dist: pyproj
Requires-Dist: dbfread
Requires-Dist: graphviz
Requires-Dist: beautifulsoup4
Requires-Dist: requests
Requires-Dist: matplotlib==3.10.*
Requires-Dist: mkl
Requires-Dist: python-gettext
Requires-Dist: shapely==2.1.*
Requires-Dist: openpyxl
Requires-Dist: xlrd
Requires-Dist: openkmi
Requires-Dist: lxml
Requires-Dist: laspy
Requires-Dist: laszip
Requires-Dist: sympy
Requires-Dist: python-pptx
Requires-Dist: python-docx
Requires-Dist: pygltflib
Requires-Dist: ezdxf
Requires-Dist: pyvista
Requires-Dist: tqdm==4.67.*
Requires-Dist: tifffile
Requires-Dist: numba==0.61.*
Requires-Dist: xmltodict
Requires-Dist: opencv-python
Requires-Dist: xarray
Requires-Dist: rasterio==1.4.3
Requires-Dist: h5py
Requires-Dist: exif
Requires-Dist: pyglm
Requires-Dist: mqtt
Requires-Dist: wradlib
Requires-Dist: seaborn
Requires-Dist: autograd
Requires-Dist: plyfile
Requires-Dist: tabulate
Requires-Dist: ipympl
Requires-Dist: contextily
Requires-Dist: pefile
Requires-Dist: wolfpydike==0.1.5
Requires-Dist: wolfhece-tools==0.0.18
Requires-Dist: PyMuPDF
Requires-Dist: eccodes
Requires-Dist: dataframe_image
Requires-Dist: pydantic
Requires-Dist: pdfplumber
